opentile/__init__.py
opentile/config.py
opentile/file.py
opentile/geometry.py
opentile/metadata.py
opentile/opentile.py
opentile/tiff_image.py
opentile/tiler.py
opentile/formats/__init__.py
opentile/formats/histech/__init__.py
opentile/formats/histech/histech_tiff_image.py
opentile/formats/histech/histech_tiff_tiler.py
opentile/formats/ndpi/__init__.py
opentile/formats/ndpi/ndpi_image.py
opentile/formats/ndpi/ndpi_metadata.py
opentile/formats/ndpi/ndpi_tile.py
opentile/formats/ndpi/ndpi_tiler.py
opentile/formats/ome/__init__.py
opentile/formats/ome/ome_tiff_image.py
opentile/formats/ome/ome_tiff_tiler.py
opentile/formats/philips/__init__.py
opentile/formats/philips/philips_tiff_image.py
opentile/formats/philips/philips_tiff_metadata.py
opentile/formats/philips/philips_tiff_tiler.py
opentile/formats/svs/__init__.py
opentile/formats/svs/svs_image.py
opentile/formats/svs/svs_metadata.py
opentile/formats/svs/svs_tiler.py
opentile/jpeg/__init__.py
opentile/jpeg/jpeg.py
opentile/jpeg/turbojpeg_patch.py
opentile-0.20.0.dist-info/METADATA
opentile-0.20.0.dist-info/WHEEL
opentile-0.20.0.dist-info/licenses/LICENCE
opentile-0.20.0.dist-info/RECORD
