Metadata-Version: 2.4
Name: opentile
Version: 0.20.0
Summary: Read tiles from wsi-TIFF files
Project-URL: Repository, https://github.com/imi-bigpicture/opentile
Author-email: Erik O Gabrielsson <erik.o.gabrielsson@sectra.com>
License: Apache-2.0
License-File: LICENCE
Keywords: digital pathology,tiff,whole slide image
Classifier: Development Status :: 4 - Beta
Classifier: Intended Audience :: Developers
Classifier: Intended Audience :: Science/Research
Classifier: Operating System :: OS Independent
Requires-Python: >=3.9
Requires-Dist: defusedxml<0.8.0,>=0.7.1
Requires-Dist: fsspec<2025.0.0,>=2024.2.0
Requires-Dist: imagecodecs>=2022.12.24
Requires-Dist: numpy>=1.22.0
Requires-Dist: ome-types<0.6.0,>=0.5.0
Requires-Dist: pillow<11.0.0,>=10.1.0
Requires-Dist: pyturbojpeg<2.0.0,>=1.7.3
Requires-Dist: tifffile>=2022.5.4
Requires-Dist: universal-pathlib<0.3.0,>=0.2.1
